{
  "preguntados": [
    {
      "id": 1,
      "pregunta": "¿Qué selección nacional ganó la primera Copa del Mundo en 1930?",
      "opciones": ["Argentina", "Uruguay", "Brasil", "Italia"],
      "correcta": "Uruguay"
    },
    {
      "id": 2,
      "pregunta": "¿Quién es el máximo goleador histórico de la UEFA Champions League?",
      "opciones": ["Lionel Messi", "Cristiano Ronaldo", "Robert Lewandowski", "Raúl González"],
      "correcta": "Cristiano Ronaldo"
    },
    {
      "id": 3,
      "pregunta": "¿Qué club inglés es el único en ganar la Premier League de forma invicta (Los Invencibles)?",
      "opciones": ["Manchester United", "Chelsea", "Manchester City", "Arsenal"],
      "correcta": "Arsenal"
    },
    {
      "id": 4,
      "pregunta": "¿En qué año se fundó la FIFA?",
      "opciones": ["1904", "1912", "1920", "1898"],
      "correcta": "1904"
    },
    {
      "id": 5,
      "pregunta": "¿Qué jugador tiene el récord de más expulsiones en la historia de la Liga de Campeones?",
      "opciones": ["Sergio Ramos", "Zlatan Ibrahimović", "Edgar Davids", "Patrick Vieira"],
      "correcta": "Zlatan Ibrahimović"
    },
    {
      "id": 6,
      "pregunta": "¿Quién fue el director técnico de la Selección de Francia en el Mundial de 1998?",
      "opciones": ["Aimé Jacquet", "Roger Lemerre", "Raymond Domenech", "Michel Platini"],
      "correcta": "Aimé Jacquet"
    },
    {
      "id": 7,
      "pregunta": "¿Qué país africano fue el primero en clasificar a unos cuartos de final en un Mundial?",
      "opciones": ["Camerún", "Senegal", "Ghana", "Marruecos"],
      "correcta": "Camerún"
    },
    {
      "id": 8,
      "pregunta": "¿Qué futbolista ganó el Balón de Oro en el año 2004?",
      "opciones": ["Ronaldinho", "Andriy Shevchenko", "Thierry Henry", "Deco"],
      "correcta": "Andriy Shevchenko"
    },
    {
      "id": 9,
      "pregunta": "¿Cuál es el club con más títulos de la Copa Libertadores de América?",
      "opciones": ["Boca Juniors", "River Plate", "Independiente", "Peñarol"],
      "correcta": "Independiente"
    },
    {
      "id": 10,
      "pregunta": "¿Quién anotó el gol de la victoria para España en la final del Mundial 2010?",
      "opciones": ["Andrés Iniesta", "Xavi Hernández", "David Villa", "Fernando Torres"],
      "correcta": "Andrés Iniesta"
    },
    {
    "id": 11,
    "pregunta": "¿Qué selección eliminó a Brasil en la final del Mundial de 1950 en el histórico 'Maracanazo'?",
    "opciones": ["Uruguay", "Argentina", "Hungría", "Italia"],
    "correcta": "Uruguay"
  },
  {
    "id": 12,
    "pregunta": "¿Qué club ganó la primera edición de la Copa de Europa en 1956?",
    "opciones": ["Real Madrid", "Benfica", "AC Milan", "Stade de Reims"],
    "correcta": "Real Madrid"
  },
  {
    "id": 13,
    "pregunta": "¿Quién es el máximo goleador histórico de la Copa Mundial de la FIFA?",
    "opciones": ["Miroslav Klose", "Ronaldo Nazário", "Gerd Müller", "Pelé"],
    "correcta": "Miroslav Klose"
  },
  {
    "id": 14,
    "pregunta": "¿Qué país organizó el primer Mundial de fútbol en 1930?",
    "opciones": ["Argentina", "Italia", "Uruguay", "Brasil"],
    "correcta": "Uruguay"
  },
  {
    "id": 15,
    "pregunta": "¿Qué jugador ganó el Balón de Oro de 1995, siendo el primer africano en conseguirlo?",
    "opciones": ["George Weah", "Samuel Eto'o", "Didier Drogba", "Abedi Pelé"],
    "correcta": "George Weah"
  },
  {
    "id": 16,
    "pregunta": "¿Qué selección ganó la Eurocopa de 2004?",
    "opciones": ["Portugal", "Grecia", "República Checa", "Francia"],
    "correcta": "Grecia"
  },
  {
    "id": 17,
    "pregunta": "¿Quién fue el máximo goleador del Mundial de Sudáfrica 2010?",
    "opciones": ["Thomas Müller", "David Villa", "Diego Forlán", "Wesley Sneijder"],
    "correcta": "Thomas Müller"
  },
  {
    "id": 18,
    "pregunta": "¿Qué club italiano descendió administrativamente a la Serie B tras el escándalo del Calciopoli?",
    "opciones": ["AC Milan", "Lazio", "Juventus", "Fiorentina"],
    "correcta": "Juventus"
  },
  {
    "id": 19,
    "pregunta": "¿Quién marcó el gol con la 'Mano de Dios' en el Mundial de 1986?",
    "opciones": ["Mario Kempes", "Diego Maradona", "Jorge Valdano", "Gabriel Batistuta"],
    "correcta": "Diego Maradona"
  },
  {
    "id": 20,
    "pregunta": "¿Qué club ganó la Champions League 2011-12 derrotando al Bayern Múnich en su propio estadio?",
    "opciones": ["Chelsea", "Manchester United", "Inter de Milán", "Real Madrid"],
    "correcta": "Chelsea"
  },
  {
    "id": 21,
    "pregunta": "¿Qué selección fue campeona del primer Mundial celebrado en Asia?",
    "opciones": ["Alemania", "Brasil", "Italia", "Francia"],
    "correcta": "Brasil"
  },
  {
    "id": 22,
    "pregunta": "¿Quién es el único portero que ha ganado el Balón de Oro?",
    "opciones": ["Lev Yashin", "Gianluigi Buffon", "Manuel Neuer", "Iker Casillas"],
    "correcta": "Lev Yashin"
  },
  {
    "id": 23,
    "pregunta": "¿Qué entrenador dirigió al Barcelona durante el histórico sextete de 2009?",
    "opciones": ["Luis Enrique", "Frank Rijkaard", "Pep Guardiola", "Tito Vilanova"],
    "correcta": "Pep Guardiola"
  },
  {
    "id": 24,
    "pregunta": "¿Qué selección perdió tres finales consecutivas de Copa América entre 2015 y 2016 y Mundial en 2014?",
    "opciones": ["Chile", "Argentina", "Brasil", "Uruguay"],
    "correcta": "Argentina"
  },
  {
    "id": 25,
    "pregunta": "¿Qué futbolista tiene el récord de más asistencias en la historia de la Champions League?",
    "opciones": ["Cristiano Ronaldo", "Lionel Messi", "Ryan Giggs", "Ángel Di María"],
    "correcta": "Cristiano Ronaldo"
  },
  {
    "id": 26,
    "pregunta": "¿Qué club ganó la primera edición de la Premier League en la temporada 1992-93?",
    "opciones": ["Manchester United", "Blackburn Rovers", "Arsenal", "Liverpool"],
    "correcta": "Manchester United"
  },
  {
    "id": 27,
    "pregunta": "¿Qué selección ganó la Copa América Centenario en 2016?",
    "opciones": ["Chile", "Argentina", "Colombia", "Brasil"],
    "correcta": "Chile"
  },
  {
    "id": 28,
    "pregunta": "¿Quién fue el máximo goleador de la Eurocopa 2016?",
    "opciones": ["Antoine Griezmann", "Cristiano Ronaldo", "Olivier Giroud", "Álvaro Morata"],
    "correcta": "Antoine Griezmann"
  },
  {
    "id": 29,
    "pregunta": "¿En qué club debutó profesionalmente Luka Modrić?",
    "opciones": ["Dinamo Zagreb", "Zrinjski Mostar", "NK Zagreb", "Inter Zaprešić"],
    "correcta": "Dinamo Zagreb"
  },
  {
    "id": 30,
    "pregunta": "¿Qué selección ganó el Mundial Sub-20 de 2005?",
    "opciones": ["Argentina", "Brasil", "Nigeria", "España"],
    "correcta": "Argentina"
  },
  {
    "id": 31,
    "pregunta": "¿Quién marcó el gol del triunfo del Manchester United en la final de la Champions League de 1999?",
    "opciones": ["Ole Gunnar Solskjær", "Teddy Sheringham", "David Beckham", "Dwight Yorke"],
    "correcta": "Ole Gunnar Solskjær"
  },
  {
    "id": 32,
    "pregunta": "¿Qué país fue sede de la Copa Mundial de 1994?",
    "opciones": ["Estados Unidos", "México", "Italia", "Francia"],
    "correcta": "Estados Unidos"
  },
  {
    "id": 33,
    "pregunta": "¿Qué jugador ganó el Balón de Oro en 2007?",
    "opciones": ["Kaká", "Cristiano Ronaldo", "Lionel Messi", "Andrea Pirlo"],
    "correcta": "Kaká"
  },
  {
    "id": 34,
    "pregunta": "¿Qué club eliminó al Barcelona en las semifinales de la Champions League 2009-10?",
    "opciones": ["Inter de Milán", "Chelsea", "Bayern Múnich", "Manchester United"],
    "correcta": "Inter de Milán"
  },
  {
    "id": 35,
    "pregunta": "¿Qué selección ganó la Copa Confederaciones 2013?",
    "opciones": ["Brasil", "España", "Italia", "Uruguay"],
    "correcta": "Brasil"
  },
  {
    "id": 36,
    "pregunta": "¿Qué club fue campeón de la Bundesliga invicto en la temporada 2023-24?",
    "opciones": ["Bayer Leverkusen", "Bayern Múnich", "Borussia Dortmund", "RB Leipzig"],
    "correcta": "Bayer Leverkusen"
  },
  {
    "id": 37,
    "pregunta": "¿Qué jugador anotó el gol de volea en la final de la Champions League 2002?",
    "opciones": ["Zinedine Zidane", "Raúl González", "Luís Figo", "Roberto Carlos"],
    "correcta": "Zinedine Zidane"
  },
  {
    "id": 38,
    "pregunta": "¿Cuál fue el primer club europeo de Ronaldinho?",
    "opciones": ["Paris Saint-Germain", "Barcelona", "AC Milan", "Porto"],
    "correcta": "Paris Saint-Germain"
  },
  {
    "id": 39,
    "pregunta": "¿Quién fue el capitán de Italia en la final del Mundial 2006?",
    "opciones": ["Fabio Cannavaro", "Francesco Totti", "Gianluigi Buffon", "Alessandro Del Piero"],
    "correcta": "Fabio Cannavaro"
  },
  {
    "id": 40,
    "pregunta": "¿Qué selección ganó la Eurocopa de 1992 tras ser invitada a último momento?",
    "opciones": ["Dinamarca", "Suecia", "Alemania", "Países Bajos"],
    "correcta": "Dinamarca"
  },
  {
    "id": 41,
    "pregunta": "¿Cuál fue el primer club de Sergio Agüero en Europa?",
    "opciones": ["Atlético de Madrid", "Manchester City", "Sevilla", "Valencia"],
    "correcta": "Atlético de Madrid"
  },
  {
    "id": 42,
    "pregunta": "¿Qué selección derrotó a Alemania en las semifinales del Mundial 2018?",
    "opciones": ["Ninguna, Alemania quedó eliminada en fase de grupos", "Francia", "Croacia", "Bélgica"],
    "correcta": "Ninguna, Alemania quedó eliminada en fase de grupos"
  },
  {
    "id": 43,
    "pregunta": "¿Quién fue el máximo goleador de la Copa América 2021?",
    "opciones": ["Lionel Messi", "Luis Díaz", "Lautaro Martínez", "Neymar"],
    "correcta": "Lionel Messi"
  },
  {
    "id": 44,
    "pregunta": "¿Qué club ganó la Europa League en 2022?",
    "opciones": ["Eintracht Frankfurt", "Rangers", "Sevilla", "West Ham"],
    "correcta": "Eintracht Frankfurt"
  },
  {
    "id": 45,
    "pregunta": "¿Qué entrenador conquistó tres Champions League consecutivas con el Real Madrid?",
    "opciones": ["Zinedine Zidane", "Carlo Ancelotti", "José Mourinho", "Vicente del Bosque"],
    "correcta": "Zinedine Zidane"
  },
  {
    "id": 46,
    "pregunta": "¿Qué país ganó la primera Eurocopa disputada en 1960?",
    "opciones": ["Unión Soviética", "España", "Yugoslavia", "Checoslovaquia"],
    "correcta": "Unión Soviética"
  },
  {
    "id": 47,
    "pregunta": "¿Qué jugador ganó el premio Golden Boy en 2018?",
    "opciones": ["Matthijs de Ligt", "Kylian Mbappé", "João Félix", "Erling Haaland"],
    "correcta": "Matthijs de Ligt"
  },
  {
    "id": 48,
    "pregunta": "¿Qué selección ganó el oro olímpico en fútbol masculino en Tokio 2020?",
    "opciones": ["Brasil", "España", "México", "Argentina"],
    "correcta": "Brasil"
  },
  {
    "id": 49,
    "pregunta": "¿Qué club fue el rival del Liverpool en la final de la Champions League 2019?",
    "opciones": ["Tottenham Hotspur", "Ajax", "Barcelona", "Manchester City"],
    "correcta": "Tottenham Hotspur"
  },
  {
    "id": 50,
    "pregunta": "¿Quién fue el entrenador de la selección argentina campeona del Mundial 2022?",
    "opciones": ["Lionel Scaloni", "Jorge Sampaoli", "Marcelo Bielsa", "Gerardo Martino"],
    "correcta": "Lionel Scaloni"
  },
  {
    "id": 51,
    "pregunta": "¿Qué selección ganó la primera Copa Confederaciones reconocida por la FIFA en 1997?",
    "opciones": ["Brasil", "Francia", "Argentina", "México"],
    "correcta": "Brasil"
  },
  {
    "id": 52,
    "pregunta": "¿Quién anotó el gol del triunfo de Alemania en la final del Mundial 2014?",
    "opciones": ["Mario Götze", "Thomas Müller", "Miroslav Klose", "André Schürrle"],
    "correcta": "Mario Götze"
  },
  {
    "id": 53,
    "pregunta": "¿Qué club ganó la primera UEFA Europa League disputada bajo ese nombre en 2010?",
    "opciones": ["Atlético de Madrid", "Fulham", "Sevilla", "Porto"],
    "correcta": "Atlético de Madrid"
  },
  {
    "id": 54,
    "pregunta": "¿Quién fue el máximo goleador de la Champions League 2014-15?",
    "opciones": ["Lionel Messi", "Cristiano Ronaldo", "Neymar", "Luis Suárez"],
    "correcta": "Cristiano Ronaldo"
  },
  {
    "id": 55,
    "pregunta": "¿Qué selección eliminó a España en los octavos de final del Mundial 2018?",
    "opciones": ["Rusia", "Croacia", "Portugal", "Uruguay"],
    "correcta": "Rusia"
  },
  {
    "id": 56,
    "pregunta": "¿Qué club fichó a Erling Haaland procedente del Red Bull Salzburg?",
    "opciones": ["Borussia Dortmund", "Manchester City", "RB Leipzig", "Bayern Múnich"],
    "correcta": "Borussia Dortmund"
  },
  {
    "id": 57,
    "pregunta": "¿Quién ganó el Balón de Oro en 2018?",
    "opciones": ["Luka Modrić", "Cristiano Ronaldo", "Lionel Messi", "Antoine Griezmann"],
    "correcta": "Luka Modrić"
  },
  {
    "id": 58,
    "pregunta": "¿Qué selección conquistó la Copa América 2011?",
    "opciones": ["Uruguay", "Paraguay", "Argentina", "Chile"],
    "correcta": "Uruguay"
  },
  {
    "id": 59,
    "pregunta": "¿Quién fue el entrenador del Leicester City campeón de la Premier League 2015-16?",
    "opciones": ["Claudio Ranieri", "Brendan Rodgers", "Nigel Pearson", "Mauricio Pochettino"],
    "correcta": "Claudio Ranieri"
  },
  {
    "id": 60,
    "pregunta": "¿Qué jugador marcó el famoso gol de chilena para el Real Madrid ante la Juventus en 2018?",
    "opciones": ["Cristiano Ronaldo", "Gareth Bale", "Karim Benzema", "Marcelo"],
    "correcta": "Cristiano Ronaldo"
  },
  {
    "id": 61,
    "pregunta": "¿Qué selección ganó la Eurocopa 2008?",
    "opciones": ["España", "Alemania", "Rusia", "Países Bajos"],
    "correcta": "España"
  },
  {
    "id": 62,
    "pregunta": "¿Qué club ganó la Champions League 2006-07?",
    "opciones": ["AC Milan", "Liverpool", "Barcelona", "Manchester United"],
    "correcta": "AC Milan"
  },
  {
    "id": 63,
    "pregunta": "¿Quién fue el máximo goleador de la Copa Libertadores 2018?",
    "opciones": ["Miguel Borja", "Lucas Pratto", "Gustavo Gómez", "Hernán Barcos"],
    "correcta": "Miguel Borja"
  },
  {
    "id": 64,
    "pregunta": "¿Qué selección fue subcampeona del Mundial de 2002?",
    "opciones": ["Alemania", "Brasil", "Turquía", "Corea del Sur"],
    "correcta": "Alemania"
  },
  {
    "id": 65,
    "pregunta": "¿En qué estadio se disputó la final del Mundial de 2014?",
    "opciones": ["Maracaná", "Mineirão", "Arena Corinthians", "Mané Garrincha"],
    "correcta": "Maracaná"
  },
  {
    "id": 66,
    "pregunta": "¿Qué club ganó la Copa Libertadores 2016?",
    "opciones": ["Atlético Nacional", "Independiente del Valle", "River Plate", "Boca Juniors"],
    "correcta": "Atlético Nacional"
  },
  {
    "id": 67,
    "pregunta": "¿Quién fue el capitán del Barcelona durante el sextete de 2009?",
    "opciones": ["Carles Puyol", "Xavi Hernández", "Andrés Iniesta", "Víctor Valdés"],
    "correcta": "Carles Puyol"
  },
  {
    "id": 68,
    "pregunta": "¿Qué país fue sede de la Eurocopa 2012 junto con Polonia?",
    "opciones": ["Ucrania", "Hungría", "Austria", "Croacia"],
    "correcta": "Ucrania"
  },
  {
    "id": 69,
    "pregunta": "¿Quién marcó el gol decisivo del Chelsea en la final de la Champions League 2021?",
    "opciones": ["Kai Havertz", "Mason Mount", "Timo Werner", "N'Golo Kanté"],
    "correcta": "Kai Havertz"
  },
  {
    "id": 70,
    "pregunta": "¿Qué club fue el rival del Barcelona en la final de la Champions League 2015?",
    "opciones": ["Juventus", "Bayern Múnich", "Atlético de Madrid", "PSG"],
    "correcta": "Juventus"
  },
  {
    "id": 71,
    "pregunta": "¿Qué selección ganó el Mundial Femenino de 2019?",
    "opciones": ["Estados Unidos", "Países Bajos", "Alemania", "Suecia"],
    "correcta": "Estados Unidos"
  },
  {
    "id": 72,
    "pregunta": "¿Quién fue el máximo goleador de la Premier League 2017-18?",
    "opciones": ["Mohamed Salah", "Harry Kane", "Sergio Agüero", "Romelu Lukaku"],
    "correcta": "Mohamed Salah"
  },
  {
    "id": 73,
    "pregunta": "¿Qué club ganó la UEFA Champions League en 1997?",
    "opciones": ["Borussia Dortmund", "Juventus", "Real Madrid", "Ajax"],
    "correcta": "Borussia Dortmund"
  },
  {
    "id": 74,
    "pregunta": "¿Qué jugador fue elegido Mejor Jugador del Mundial de 2018?",
    "opciones": ["Luka Modrić", "Kylian Mbappé", "Antoine Griezmann", "Eden Hazard"],
    "correcta": "Luka Modrić"
  },
  {
    "id": 75,
    "pregunta": "¿Qué país ganó la Copa Africana de Naciones 2019?",
    "opciones": ["Argelia", "Senegal", "Egipto", "Nigeria"],
    "correcta": "Argelia"
  },
  {
    "id": 76,
    "pregunta": "¿Quién fue el entrenador del Inter campeón de la Champions League 2010?",
    "opciones": ["José Mourinho", "Roberto Mancini", "Rafael Benítez", "Luciano Spalletti"],
    "correcta": "José Mourinho"
  },
  {
    "id": 77,
    "pregunta": "¿Qué club ganó la Copa Sudamericana 2019?",
    "opciones": ["Independiente del Valle", "Colón", "Athletico Paranaense", "Fluminense"],
    "correcta": "Independiente del Valle"
  },
  {
    "id": 78,
    "pregunta": "¿Qué selección fue campeona de la Copa Asiática 2019?",
    "opciones": ["Catar", "Japón", "Corea del Sur", "Australia"],
    "correcta": "Catar"
  },
  {
    "id": 79,
    "pregunta": "¿Quién fue el máximo goleador de la Serie A 2019-20?",
    "opciones": ["Ciro Immobile", "Cristiano Ronaldo", "Romelu Lukaku", "Zlatan Ibrahimović"],
    "correcta": "Ciro Immobile"
  },
  {
    "id": 80,
    "pregunta": "¿Qué club ganó la primera edición del Mundial de Clubes de la FIFA en el año 2000?",
    "opciones": ["Corinthians", "Vasco da Gama", "Manchester United", "Real Madrid"],
    "correcta": "Corinthians"
  },
  {
    "id": 81,
    "pregunta": "¿Qué club ganó la primera Copa Libertadores disputada en 1960?",
    "opciones": ["Peñarol", "Olimpia", "Independiente", "Bahía"],
    "correcta": "Peñarol"
  },
  {
    "id": 82,
    "pregunta": "¿Quién fue el máximo goleador del Mundial de Francia 1998?",
    "opciones": ["Davor Šuker", "Ronaldo", "Gabriel Batistuta", "Christian Vieri"],
    "correcta": "Davor Šuker"
  },
  {
    "id": 83,
    "pregunta": "¿Qué club eliminó al Real Madrid en los octavos de final de la Champions League 2018-19?",
    "opciones": ["Ajax", "Manchester City", "Juventus", "Liverpool"],
    "correcta": "Ajax"
  },
  {
    "id": 84,
    "pregunta": "¿Qué selección ganó la Copa América de 2015?",
    "opciones": ["Chile", "Argentina", "Uruguay", "Colombia"],
    "correcta": "Chile"
  },
  {
    "id": 85,
    "pregunta": "¿Quién marcó el gol de la victoria del Barcelona en la final de la Champions League 2006?",
    "opciones": ["Juliano Belletti", "Samuel Eto'o", "Ronaldinho", "Ludovic Giuly"],
    "correcta": "Juliano Belletti"
  },
  {
    "id": 86,
    "pregunta": "¿Qué entrenador llevó a Portugal a conquistar la Eurocopa 2016?",
    "opciones": ["Fernando Santos", "Paulo Bento", "Carlos Queiroz", "Luiz Felipe Scolari"],
    "correcta": "Fernando Santos"
  },
  {
    "id": 87,
    "pregunta": "¿Qué selección ganó el Mundial Sub-17 de 2019?",
    "opciones": ["Brasil", "México", "Francia", "España"],
    "correcta": "Brasil"
  },
  {
    "id": 88,
    "pregunta": "¿Qué club ganó la Champions League en 1995?",
    "opciones": ["Ajax", "AC Milan", "Juventus", "Benfica"],
    "correcta": "Ajax"
  },
  {
    "id": 89,
    "pregunta": "¿Quién fue el primer jugador en ganar cinco Balones de Oro?",
    "opciones": ["Lionel Messi", "Cristiano Ronaldo", "Johan Cruyff", "Michel Platini"],
    "correcta": "Lionel Messi"
  },
  {
    "id": 90,
    "pregunta": "¿Qué selección perdió la final del Mundial 2010?",
    "opciones": ["Países Bajos", "Alemania", "Uruguay", "Brasil"],
    "correcta": "Países Bajos"
  },
  {
    "id": 91,
    "pregunta": "¿Qué jugador anotó el famoso gol desde mitad de cancha ante Inglaterra en el Mundial 2002?",
    "opciones": ["Ronaldinho", "Rivaldo", "Ronaldo", "Cafu"],
    "correcta": "Ronaldinho"
  },
  {
    "id": 92,
    "pregunta": "¿Qué club fue campeón de la Champions League 1998-99?",
    "opciones": ["Manchester United", "Bayern Múnich", "Real Madrid", "Juventus"],
    "correcta": "Manchester United"
  },
  {
    "id": 93,
    "pregunta": "¿Quién ganó el Balón de Oro en 2006?",
    "opciones": ["Fabio Cannavaro", "Zinedine Zidane", "Ronaldinho", "Thierry Henry"],
    "correcta": "Fabio Cannavaro"
  },
  {
    "id": 94,
    "pregunta": "¿Qué selección fue campeona del Mundial de 1978?",
    "opciones": ["Argentina", "Países Bajos", "Brasil", "Italia"],
    "correcta": "Argentina"
  },
  {
    "id": 95,
    "pregunta": "¿Qué club ganó la Copa Sudamericana 2015?",
    "opciones": ["Santa Fe", "River Plate", "Atlético Nacional", "Lanús"],
    "correcta": "Santa Fe"
  },
  {
    "id": 96,
    "pregunta": "¿Quién fue el máximo goleador de la Copa América 2015?",
    "opciones": ["Eduardo Vargas", "Lionel Messi", "Paolo Guerrero", "Alexis Sánchez"],
    "correcta": "Eduardo Vargas"
  },
  {
    "id": 97,
    "pregunta": "¿Qué selección ganó la Eurocopa 1988?",
    "opciones": ["Países Bajos", "Alemania Federal", "Unión Soviética", "Italia"],
    "correcta": "Países Bajos"
  },
  {
    "id": 98,
    "pregunta": "¿Qué club fichó a Neymar procedente del Santos?",
    "opciones": ["Barcelona", "Real Madrid", "PSG", "Chelsea"],
    "correcta": "Barcelona"
  },
  {
    "id": 99,
    "pregunta": "¿Quién fue el entrenador de España campeona del Mundial 2010?",
    "opciones": ["Vicente del Bosque", "Luis Aragonés", "Julen Lopetegui", "Pep Guardiola"],
    "correcta": "Vicente del Bosque"
  },
  {
    "id": 100,
    "pregunta": "¿Qué selección ganó la Copa Oro de la CONCACAF en 2021?",
    "opciones": ["Estados Unidos", "México", "Canadá", "Costa Rica"],
    "correcta": "Estados Unidos"
  },
  {
    "id": 101,
    "pregunta": "¿Qué jugador fue el máximo goleador de la Liga española 2012-13?",
    "opciones": ["Lionel Messi", "Cristiano Ronaldo", "Radamel Falcao", "Diego Costa"],
    "correcta": "Lionel Messi"
  },
  {
    "id": 102,
    "pregunta": "¿Qué club ganó la Copa Libertadores 2021?",
    "opciones": ["Palmeiras", "Flamengo", "River Plate", "Atlético Mineiro"],
    "correcta": "Palmeiras"
  },
  {
    "id": 103,
    "pregunta": "¿Quién marcó el gol del empate del Barcelona en la final de Champions 2006 antes del tanto decisivo?",
    "opciones": ["Samuel Eto'o", "Ronaldinho", "Deco", "Xavi"],
    "correcta": "Samuel Eto'o"
  },
  {
    "id": 104,
    "pregunta": "¿Qué país fue sede de la Copa América 2019?",
    "opciones": ["Brasil", "Chile", "Argentina", "Estados Unidos"],
    "correcta": "Brasil"
  },
  {
    "id": 105,
    "pregunta": "¿Qué club ganó la Recopa de Europa por última vez antes de desaparecer la competición?",
    "opciones": ["Lazio", "Chelsea", "Arsenal", "Valencia"],
    "correcta": "Lazio"
  },
  {
    "id": 106,
    "pregunta": "¿Qué selección ganó la Copa Asiática 2011?",
    "opciones": ["Japón", "Australia", "Corea del Sur", "Irán"],
    "correcta": "Japón"
  },
  {
    "id": 107,
    "pregunta": "¿Quién fue el máximo goleador de la Champions League 2012-13?",
    "opciones": ["Cristiano Ronaldo", "Lionel Messi", "Robert Lewandowski", "Thomas Müller"],
    "correcta": "Cristiano Ronaldo"
  },
  {
    "id": 108,
    "pregunta": "¿Qué club ganó la UEFA Champions League 2000-01?",
    "opciones": ["Bayern Múnich", "Valencia", "Real Madrid", "Manchester United"],
    "correcta": "Bayern Múnich"
  },
  {
    "id": 109,
    "pregunta": "¿Quién fue el capitán de Francia en el Mundial de 1998?",
    "opciones": ["Didier Deschamps", "Zinedine Zidane", "Marcel Desailly", "Laurent Blanc"],
    "correcta": "Didier Deschamps"
  },
  {
    "id": 110,
    "pregunta": "¿Qué selección ganó la Copa América de 1995?",
    "opciones": ["Uruguay", "Brasil", "Argentina", "Colombia"],
    "correcta": "Uruguay"
  }
  ],
  "adivina_jugador": [
    {
      "id": 1,
      "historial": "Malmo FF 🇸🇪 ➔ Ajax 🇳🇱 ➔ Juventus 🇮🇹 ➔ Inter de Milán 🇮🇹 ➔ Barcelona 🇪🇸 ➔ AC Milan 🇮🇹 ➔ PSG 🇫🇷 ➔ Manchester United 🇬🇧 ➔ LA Galaxy 🇺🇸 ➔ AC Milan 🇮🇹",
      "nombre": "Zlatan Ibrahimovic"
    },
    {
      "id": 2,
      "historial": "River Plate 🇦🇷 ➔ Real Madrid 🇪🇸 ➔ Napoli 🇮🇹 ➔ Juventus 🇮🇹 ➔ AC Milan 🇮🇹 ➔ Chelsea 🇬🇧 ➔ Inter Miami 🇺🇸",
      "nombre": "Gonzalo Higuain"
    },
    {
      "id": 3,
      "historial": "Sporting CP 🇵🇹 ➔ Manchester United 🇬🇧 ➔ Real Madrid 🇪🇸 ➔ Juventus 🇮🇹 ➔ Manchester United 🇬🇧 ➔ Al-Nassr 🇸🇦",
      "nombre": "Cristiano Ronaldo"
    },
    {
      "id": 4,
      "historial": "Monaco 🇫🇷 ➔ Juventus 🇮🇹 ➔ Arsenal 🇬🇧 ➔ Barcelona 🇪🇸 ➔ New York Red Bulls 🇺🇸",
      "nombre": "Thierry Henry"
    },
    {
      "id": 5,
      "historial": "Nacional 🇺🇾 ➔ Groningen 🇳🇱 ➔ Ajax 🇳🇱 ➔ Liverpool 🇬🇧 ➔ Barcelona 🇪🇸 ➔ Atlético de Madrid 🇪🇸 ➔ Nacional 🇺🇾 ➔ Grêmio 🇧🇷 ➔ Inter Miami 🇺🇸",
      "nombre": "Luis Suarez"
    },
    {
      "id": 6,
      "historial": "Boca Juniors 🇦🇷 ➔ Corinthians 🇧🇷 ➔ West Ham 🇬🇧 ➔ Manchester United 🇬🇧 ➔ Manchester City 🇬🇧 ➔ Juventus 🇮🇹 ➔ Boca Juniors 🇦🇷 ➔ Shanghai Shenhua 🇨🇳 ➔ Boca Juniors 🇦🇷",
      "nombre": "Carlos Tevez"
    },
    {
      "id": 7,
      "historial": "Parma 🇮🇹 ➔ Juventus 🇮🇹 ➔ PSG 🇫🇷 ➔ Juventus 🇮🇹 ➔ Parma 🇮🇹",
      "nombre": "Gianluigi Buffon"
    },
    {
      "id": 8,
      "historial": "Real Sociedad 🇪🇸 ➔ Liverpool 🇬🇧 ➔ Real Madrid 🇪🇸 ➔ Bayern Múnich 🇩🇪",
      "nombre": "Xabi Alonso"
    },
  {
    "id": 9,
    "historial": "Newell's Old Boys 🇦🇷 ➔ Barcelona 🇪🇸 ➔ PSG 🇫🇷 ➔ Inter Miami 🇺🇸",
    "nombre": "Lionel Messi"
  },
  {
    "id": 10,
    "historial": "Santos 🇧🇷 ➔ Barcelona 🇪🇸 ➔ PSG 🇫🇷 ➔ Al-Hilal 🇸🇦 ➔ Santos 🇧🇷",
    "nombre": "Neymar"
  },
  {
    "id": 11,
    "historial": "Independiente 🇦🇷 ➔ Atlético de Madrid 🇪🇸 ➔ Manchester City 🇬🇧",
    "nombre": "Sergio Agüero"
  },
  {
    "id": 12,
    "historial": "Rosario Central 🇦🇷 ➔ Benfica 🇵🇹 ➔ Real Madrid 🇪🇸 ➔ Manchester United 🇬🇧 ➔ PSG 🇫🇷 ➔ Juventus 🇮🇹 ➔ Benfica 🇵🇹 ➔ Rosario Central 🇦🇷",
    "nombre": "Ángel Di María"
  },
  {
    "id": 13,
    "historial": "Argentinos Juniors 🇦🇷 ➔ Boca Juniors 🇦🇷 ➔ Juventus 🇮🇹 ➔ Tottenham Hotspur",
    "nombre": "Rodrigo Bentancur"
  },
  {
    "id": 14,
    "historial": "Danubio 🇺🇾 ➔ Palermo 🇮🇹 ➔ Napoli 🇮🇹 ➔ PSG 🇫🇷 ➔ Manchester United 🇬🇧 ➔ Valencia 🇪🇸 ➔ Boca Juniors 🇦🇷",
    "nombre": "Edinson Cavani"
  },
  {
    "id": 15,
    "historial": "Nacional 🇺🇾 ➔ FC Groningen 🇳🇱 ➔ Ajax 🇳🇱 ➔ Liverpool 🇬🇧 ➔ Barcelona 🇪🇸 ➔ Atlético de Madrid 🇪🇸 ➔ Nacional 🇺🇾",
    "nombre": "Luis Suárez"
  },
  {
    "id": 16,
    "historial": "Fluminense 🇧🇷 ➔ Real Madrid 🇪🇸 ➔ Olympiacos F.C➔ Fluminense 🇧🇷",
    "nombre": "Marcelo Vieira"
  },
  {
    "id": 17,
    "historial": "São Paulo 🇧🇷 ➔ AC Milan 🇮🇹 ➔ Real Madrid 🇪🇸 ➔ Orlando City 🇺🇸",
    "nombre": "Kaká"
  },
  {
    "id": 18,
    "historial": "Cruzeiro 🇧🇷 ➔ PSV 🇳🇱 ➔ Barcelona 🇪🇸 ➔ AC Milan 🇮🇹 ➔ Corinthians 🇧🇷",
    "nombre": "Ronaldo Nazário"
  },
  {
    "id": 19,
    "historial": "Ajax 🇳🇱 ➔ Juventus 🇮🇹 ➔ Bayern Múnich 🇩🇪",
    "nombre": "Matthijs de Ligt"
  },
  {
    "id": 20,
    "historial": "Benfica 🇵🇹 ➔ Atlético de Madrid 🇪🇸 ➔ Chelsea 🇬🇧 ➔ Al-Nassr F. C.",
    "nombre": "João Félix"
  },
  {
    "id": 21,
    "historial": "C.A. Fenix 🇺🇾 ➔ F.C Famalicao ➔Sporting C.P ➔ PSG 🇫🇷 ➔ Manchester United 🇬🇧",
    "nombre": "Manuel Ugarte"
  },
  {
    "id": 22,
    "historial": "Sporting CP 🇵🇹 ➔ Manchester United 🇬🇧",
    "nombre": "Bruno Fernandes"
  },
  {
    "id": 23,
    "historial": "Independiente 🇦🇷 ➔ Manchester United 🏴🇬🇧 ➔ Villarreal 🇪🇸 ➔ Atlético de Madrid 🇪🇸 ➔ Inter de Milán 🇮🇹 ➔ Internacional 🇧🇷 ➔ Cerezo Osaka 🇯🇵 ➔ Peñarol 🇺🇾 ➔ Mumbai City 🇮🇳 ➔ Kitchee 🇭🇰",
    "nombre": "Diego Forlán"
  },
  {
    "id": 24,
    "historial": "River Plate 🇦🇷 ➔ Atlético de Madrid 🇪🇸 ➔ Sevilla 🇪🇸 ➔ Zenit de San Petersburgo 🇷🇺 ➔ Monterrey 🇲🇽 ➔ River Plate 🇦🇷 ➔ Fatih Karagümrük 🇹🇷 ➔ Racing 🇦🇷 ",
    "nombre": "Matías Kranevitter"
  },
  {
    "id": 25,
    "historial": "River Plate 🇦🇷 ➔ Corinthians 🇧🇷 ➔ West Ham 🇬🇧 ➔ Liverpool 🇬🇧 ➔ FC Barcelona 🇪🇸 ➔ Hebei China Fortune 🇨🇳 ➔ Estudiantes de La Plata 🇦🇷",
    "nombre": "Javier Mascherano"
  },
  {
    "id": 26,
    "historial": "Estudiantes de La Plata 🇦🇷 ➔ Boca Juniors 🇦🇷 ➔ Sampdoria 🇮🇹 ➔ Parma 🇮🇹 ➔ Lazio 🇮🇹 ➔ Manchester United 🏴🇬🇧 ➔ Chelsea 🏴🇬🇧 ➔ Inter de Milán 🇮🇹 ➔ Estudiantes de La Plata 🇦🇷",
    "nombre": "Juan Sebastián Verón"
  },
  {
    "id": 27,
   "historial": "Racing Club 🇦🇷 ➔ Genoa 🇮🇹 ➔ Real Zaragoza 🇪🇸 ➔ Genoa 🇮🇹 ➔ Inter de Milán 🇮🇹 ➔ Racing Club 🇦🇷",
    "nombre": "Diego Milito"
  },
  {
    "id": 28,
    "historial": "Sporting Cristal 🇵🇪 ➔ Twente 🇳🇱 ➔ Feyenoord 🇳🇱 ➔ Willem II 🇳🇱 ➔ Celta de Vigo 🇪🇸 ➔ Leganés 🇪🇸 ➔ Al Wasl 🇦🇪",
    "nombre": "Renato Tapia"
  },
  {
    "id": 29,
    "historial": "Colo-Colo 🇨🇱 ➔ Bayer Leverkusen 🇩🇪 ➔ Juventus 🇮🇹 ➔ Bayern Múnich 🇩🇪 ➔ FC Barcelona 🇪🇸 ➔ Inter de Milán 🇮🇹 ➔ Flamengo 🇧🇷 ➔ Athletico Paranaense 🇧🇷 ➔ Colo-Colo 🇨🇱",
    "nombre": "Arturo Vidal"
  },
  {
    "id": 30,
    "historial": "Cobreloa 🇨🇱 ➔ Colo-Colo 🇨🇱 ➔ River Plate 🇦🇷 ➔ Udinese 🇮🇹 ➔ FC Barcelona 🇪🇸 ➔ Arsenal 🏴🇬🇧 ➔ Manchester United 🏴🇬🇧 ➔ Inter de Milán 🇮🇹 ➔ Olympique de Marsella 🇫🇷 ➔ Inter de Milán 🇮🇹 ➔ Udinese 🇮🇹",
    "nombre": "Alexis Sánchez"
  },
  {
    "id": 31,
    "historial": "Lorient 🇫🇷 ➔ Lyon 🇫🇷 ➔ Real Madrid 🇪🇸 ➔ Al-Ittihad 🇸🇦",
    "nombre": "Karim Benzema"
  },
  {
    "id": 32,
    "historial": "Le Havre 🇫🇷 ➔ Monaco 🇫🇷 ➔ PSG 🇫🇷 ➔ Real Madrid 🇪🇸",
    "nombre": "Kylian Mbappé"
  },
  {
    "id": 33,
    "historial": "Lech Poznań 🇵🇱 ➔ Borussia Dortmund 🇩🇪 ➔ Bayern Múnich 🇩🇪 ➔ Barcelona 🇪🇸",
    "nombre": "Robert Lewandowski"
  },
  {
    "id": 34,
    "historial": "Genk 🇧🇪 ➔ Chelsea 🇬🇧 ➔ Werder Bremen 🇩🇪 ➔ Wolfsburgo 🇩🇪 ➔ Manchester City 🇬🇧",
    "nombre": "Kevin De Bruyne"
  },
  {
    "id": 35,
    "historial": "Molde 🇳🇴 ➔ Red Bull Salzburg 🇦🇹 ➔ Borussia Dortmund 🇩🇪 ➔ Manchester City 🇬🇧",
    "nombre": "Erling Haaland"
  },
  {
    "id": 36,
    "historial": "Flamengo 🇧🇷 ➔ Real Madrid 🇪🇸 ➔ Manchester City 🇬🇧 ➔ Fluminense 🇧🇷",
    "nombre": "Robinho"
  },
  {
    "id": 37,
    "historial": "São Paulo 🇧🇷 ➔ Shakhtar Donetsk 🇺🇦 ➔ AC Milan 🇮🇹 ➔ Orlando City 🇺🇸",
    "nombre": "Alexandre Pato"
  },
  {
    "id": 38,
    "historial": "Boca Juniors 🇦🇷 ➔ Valencia 🇪🇸 ➔ Atlético de Madrid 🇪🇸 ➔ Villarreal 🇪🇸 ➔ Juventus 🇮🇹",
    "nombre": "Nicolás Gaitán"
  },
  {
    "id": 39,
    "historial": "Flamengo 🇧🇷 ➔ Inter de Milán 🇮🇹 ➔ Real Madrid 🇪🇸 ➔ Manchester City 🇬🇧 ➔ Fenerbahçe 🇹🇷",
    "nombre": "Roberto Carlos"
  },
  {
    "id": 40,
    "historial": "Atlético Nacional 🇨🇴 ➔ River Plate 🇦🇷 ➔ Villarreal 🇪🇸 ➔ Atlético de Madrid 🇪🇸 ➔ Monaco 🇲🇨 ➔ Juventus 🇮🇹 ➔ Manchester United 🇬🇧",
    "nombre": "Radamel Falcao"
  },
  {
    "id": 41,
    "historial": "Independiente 🇦🇷 ➔ Real Madrid 🇪🇸 ➔ Inter de Milán 🇮🇹 ➔ Lazio 🇮🇹 ➔ Inter de Milán 🇮🇹",
    "nombre": "Esteban Cambiasso"
  },
  {
    "id": 42,
    "historial": "River Plate 🇦🇷 ➔ Monaco 🇫🇷 ➔ PSG 🇫🇷 ➔ Manchester United 🇬🇧 ➔ Chelsea 🇬🇧➔ Manchester City 🇬🇧",
    "nombre": "Ángel Di María"
  },
  {
    "id": 43,
    "historial": "Ajax 🇳🇱 ➔ Juventus 🇮🇹 ➔ Inter de Milán 🇮🇹 ➔ Real Madrid 🇪🇸 ➔ Inter de Milán 🇮🇹",
    "nombre": "Clarence Seedorf"
  },
  {
    "id": 44,
    "historial": "Boca Juniors 🇦🇷 ➔ Barcelona 🇪🇸 ➔ Napoli 🇮🇹 ➔ Boca Juniors 🇦🇷",
    "nombre": "Diego Maradona"
  },
  {
    "id": 45,
    "historial": "Metz 🇫🇷 ➔ Juventus 🇮🇹 ➔ Real Madrid 🇪🇸 ➔ Juventus 🇮🇹 ➔ Chelsea 🇬🇧",
    "nombre": "Zinedine Zidane"
  },
  {
    "id": 46,
    "historial": "River Plate 🇦🇷 ➔ Parma 🇮🇹 ➔ Lazio 🇮🇹 ➔ Inter de Milán 🇮🇹 ➔ Lazio 🇮🇹",
    "nombre": "Hernán Crespo"
  },
  {
    "id": 47,
    "historial": "Bayern Múnich 🇩🇪 ➔ Inter de Milán 🇮🇹 ➔ Real Madrid 🇪🇸 ➔ Bayern Múnich 🇩🇪",
    "nombre": "Lothar Matthäus"
  },
  {
    "id": 48,
    "historial": "Santos 🇧🇷 ➔ Real Madrid 🇪🇸 ➔ AC Milan 🇮🇹 ➔ Orlando City 🇺🇸",
    "nombre": "Kaká"
  },
  {
    "id": 49,
    "historial": "Ajax 🇳🇱 ➔ Real Madrid 🇪🇸 ➔ Inter de Milán 🇮🇹 ➔ Tottenham 🇬🇧 ➔ Fulham 🇬🇧",
    "nombre": "Rafael van der Vaart"
  },
  {
    "id": 50,
    "historial": "Lyon 🇫🇷 ➔ Real Madrid 🇪🇸 ➔ Al-Ittihad 🇸🇦",
    "nombre": "Karim Benzema"
  },
  {
    "id": 51,
    "historial": "Bordeaux 🇫🇷 ➔ Juventus 🇮🇹 ➔ Arsenal 🇬🇧 ➔ Barcelona 🇪🇸 ➔ New York Red Bulls 🇺🇸",
    "nombre": "Thierry Henry"
  },
  {
    "id": 52,
    "historial": "Rosario Central 🇦🇷 ➔ Valencia 🇪🇸 ➔ Barcelona 🇪🇸 ➔ Villarreal 🇪🇸 ➔ Manchester City 🇬🇧",
    "nombre": "Pablo Zabaleta"
  },
  {
    "id": 53,
    "historial": "River Plate 🇦🇷 ➔ Real Madrid 🇪🇸 ➔ Manchester City 🇬🇧 ➔ Monaco 🇲🇨 ➔ Espanyol 🇪🇸",
    "nombre": "Martín Demichelis"
  },
  {
    "id": 54,
    "historial": "Benfica 🇵🇹 ➔ Chelsea 🇬🇧 ➔ Real Madrid 🇪🇸 ➔ Monaco 🇲🇨 ➔ Manchester United 🇬🇧",
    "nombre": "Ricardo Carvalho"
  },
  {
    "id": 55,
    "historial": "Flamengo 🇧🇷 ➔ Porto 🇵🇹 ➔ Barcelona 🇪🇸 ➔ Inter de Milán 🇮🇹 ➔ Juventus 🇮🇹",
    "nombre": "Adriano"
  },
  {
    "id": 56,
    "historial": "River Plate 🇦🇷 ➔ Real Madrid 🇪🇸 ➔ Benfica 🇵🇹 ➔ Monaco 🇲🇨 ➔ Manchester City 🇬🇧",
    "nombre": "Javier Saviola"
  },
  {
    "id": 57,
    "historial": "Ajax 🇳🇱 ➔ Arsenal 🇬🇧 ➔ Manchester United 🇬🇧 ➔ Fenerbahçe 🇹🇷",
    "nombre": "Robin van Persie"
  },
  {
    "id": 58,
    "historial": "Porto 🇵🇹 ➔ Barcelona 🇪🇸 ➔ Chelsea 🏴 ➔ Fluminense 🇧🇷",
    "nombre": "Deco"
  },
  {
    "id": 59,
    "historial": "Anderlecht 🇧🇪 ➔ Chelsea 🇬🇧 ➔ Manchester City 🇬🇧 ➔ Wolfsburgo 🇩🇪 ➔ Manchester City 🇬🇧",
    "nombre": "Kevin De Bruyne"
  },
  {
    "id": 60,
    "historial": "Schalke 04 🇩🇪 ➔ Werder Bremen ➔ Real Madrid 🇪🇸 ➔ Arsenal 🇬🇧 ➔ Fenerbahçe 🇹🇷 ➔ İstanbul Başakşehir F. K.",
    "nombre": "Mesut Özil"
  },
  {
    "id": 61,
    "historial": "Bayern Múnich 🇩🇪 ➔ Manchester United 🇬🇧 ➔ Chicago Fire 🇺🇸",
    "nombre": "Bastian Schweinsteiger"
  },
  {
    "id": 62,
    "historial": "Dinamo Zagreb 🇭🇷 ➔ Tottenham 🇬🇧 ➔ Real Madrid 🇪🇸 ➔ Inter Milan",
    "nombre": "Luka Modrić"
  },
  {
    "id": 63,
    "historial": "Dinamo Zagreb 🇭🇷 ➔ Sevilla 🇪🇸 ➔ Real Madrid 🇪🇸 ➔ Chelsea 🇬🇧 ➔ Real Madrid 🇪🇸",
    "nombre": "Mateo Kovačić"
  },
  {
    "id": 64,
    "historial": "Newell's Old Boys 🇦🇷 ➔ Racing de Santander 🇪🇸 ➔ Real Madrid 🇪🇸 ➔ Benfica 🇵🇹 ➔ Zenit de San Petersburgo 🇷🇺 ➔ Valencia 🇪🇸",
    "nombre": "Ezequiel Garay"
  },
  {
    "id": 65,
    "historial": "Sporting CP 🇵🇹 ➔ Barcelona 🇪🇸 ➔ Real Madrid 🇪🇸 ➔ Inter de Milán 🇮🇹",
    "nombre": "Luis Figo"
  },
  {
    "id": 66,
    "historial": "Flamengo 🇧🇷 ➔ Roma 🇮🇹 ➔ Real Madrid 🇪🇸 ➔ AC Milan 🇮🇹 ➔ Real Madrid 🇪🇸",
    "nombre": "Cafu"
  },
  {
    "id": 67,
    "historial": "Racing Club 🇦🇷 ➔ Inter de Milán 🇮🇹 ➔ Real Madrid 🇪🇸 ➔ Manchester City 🇬🇧 ➔ Roma 🇮🇹",
    "nombre": "Walter Samuel"
  },
  {
    "id": 68,
   "historial": "Rio Ave 🇵🇹 ➔ Belenenses 🇵🇹 ➔ Sesimbra 🇵🇹 ➔ Lisboa  🇵🇹 ➔ Comércio e Indústria 🇵🇹 ",
    "nombre": "José Mourinho"
  }
  ],
  "palabras_mr_white": [
    "Lionel Messi",
    "Cristiano Ronaldo",
    "Diego Maradona",
    "Pelé",
    "Zinedine Zidane",
    "Ronaldinho",
    "Ronaldo Nazário",
    "Neymar",
    "Kylian Mbappé",
    "Erling Haaland",
    "Robert Lewandowski",
    "Kevin De Bruyne",
    "Luka Modrić",
    "Toni Kroos",
    "Karim Benzema",
    "Sergio Ramos",
    "Andrés Iniesta",
    "Xavi Hernández",
    "Gerard Piqué",
    "Iker Casillas",
    "Manuel Neuer",
    "Gianluigi Buffon",
    "Thibaut Courtois",
    "Virgil van Dijk",
    "Mohamed Salah",
    "Sadio Mané",
    "Harry Kane",
    "Son Heung-min",
    "Antoine Griezmann",
    "Paul Pogba",
    "N'Golo Kanté",
    "Eden Hazard",
    "Gareth Bale",
    "Luis Suárez",
    "Edinson Cavani",
    "Ángel Di María",
    "Paulo Dybala",
    "Lautaro Martínez",
    "Julián Álvarez",
    "Emiliano Martínez",
    "Rodrigo De Paul",
    "Enzo Fernández",
    "Alexis Mac Allister",
    "Carlos Tévez",
    "Sergio Agüero",
    "Javier Mascherano",
    "Juan Román Riquelme",
    "Pablo Aimar",
    "Hernán Crespo",
    "Gabriel Batistuta",
    "Javier Zanetti",
    "Esteban Cambiasso",
    "Walter Samuel",
    "Juan Sebastián Verón",
    "Rivaldo",
    "Kaká",
    "Roberto Carlos",
    "Cafu",
    "Dani Alves",
    "Marcelo",
    "Thiago Silva",
    "Casemiro",
    "Vinícius Jr.",
    "Rodrygo",
    "Richarlison",
    "Gabriel Jesus",
    "Romário",
    "Adriano",
    "Bebeto",
    "Rivaldo",
    "Sócrates",
    "Garrincha",
    "Franz Beckenbauer",
    "Gerd Müller",
    "Miroslav Klose",
    "Thomas Müller",
    "Philipp Lahm",
    "Bastian Schweinsteiger",
    "Mesut Özil",
    "Marco Reus",
    "Mats Hummels",
    "Joshua Kimmich",
    "Jamal Musiala",
    "Arjen Robben",
    "Franck Ribéry",
    "Robin van Persie",
    "Wesley Sneijder",
    "Clarence Seedorf",
    "Ruud Gullit",
    "Marco van Basten",
    "Johan Cruyff",
    "Dennis Bergkamp",
    "Patrick Vieira",
    "Thierry Henry",
    "Eric Cantona",
    "Wayne Rooney",
    "David Beckham",
    "Steven Gerrard",
    "Frank Lampard",
    "John Terry",
    "Rio Ferdinand",
    "Ashley Cole",
    "Ryan Giggs",
    "Paul Scholes",
    "Didier Drogba",
    "Samuel Eto'o",
    "Yaya Touré",
    "George Weah",
    "Sadio Mané",
    "Riyad Mahrez",
    "Achraf Hakimi",
    "Victor Osimhen",
    "Khvicha Kvaratskhelia",
    "Paulo Futre",
    "Luis Figo",
    "Deco",
    "Pepe",
    "Bruno Fernandes",
    "Bernardo Silva",
    "Rúben Dias",
    "João Félix",
    "Ricardo Quaresma",
    "Radamel Falcao",
    "James Rodríguez",
    "Juan Cuadrado",
    "Yerry Mina",
    "David Villa",
    "Fernando Torres",
    "Cesc Fàbregas",
    "David Silva",
    "Santi Cazorla",
    "Fernando Hierro",
    "Carles Puyol",
    "Sergio Busquets",
    "Zlatan Ibrahimović",
    "Andrea Pirlo",
    "Gianfranco Zola",
    "Alessandro Del Piero",
    "Francesco Totti",
    "Fabio Cannavaro",
    "Paolo Maldini",
    "Andrea Barzagli",
    "Leonardo Bonucci",
    "Giorgio Chiellini",
    "Marco Materazzi",
    "Daniele De Rossi",
    "Claudio Marchisio",
    "Antonio Cassano",
    "Mario Balotelli",
    "Ciro Immobile",
    "Lorenzo Insigne",
    "Federico Chiesa",
    "Nicolò Barella",
    "Jorginho",
    "Donnarumma",
    "Achraf Hakimi",
    "Hakim Ziyech",
    "Yassine Bounou",
    "Sofyan Amrabat",
    "Riyad Mahrez",
    "Yaya Touré",
    "Kolo Touré",
    "Didier Zokora",
    "Michael Essien",
    "John Obi Mikel",
    "Victor Osimhen",
    "Wilfried Zaha",
    "Pierre-Emerick Aubameyang",
    "Emmanuel Adebayor",
    "Jay-Jay Okocha",
    "Nwankwo Kanu",
    "Salomon Kalou",
    "Frederic Kanouté",
    "Samuel Kuffour",
    "Asamoah Gyan",
    "Thomas Partey",
    "Kwadwo Asamoah",
    "Son Heung-min",
    "Park Ji-sung",
    "Keisuke Honda",
    "Shinji Kagawa",
    "Takefusa Kubo",
    "Hidetoshi Nakata",
    "Ali Daei",
    "Mehdi Taremi",
    "Tim Cahill",
    "Harry Kewell",
    "Mark Viduka",
    "Carlos Valderrama",
    "René Higuita",
    "Faustino Asprilla",
    "Iván Córdoba",
    "Juan Pablo Ángel",
    "Claudio Bravo",
    "Arturo Vidal",
    "Gary Medel",
    "Alexis Sánchez",
    "Marcelo Salas",
    "Iván Zamorano",
    "José Luis Chilavert",
    "Óscar Cardozo",
    "Roque Santa Cruz",
    "Salvador Cabañas",
    "Paolo Guerrero",
    "Jefferson Farfán",
    "Claudio Pizarro",
    "Teófilo Gutiérrez",
    "Radamel Falcao",
    "Jackson Martínez",
    "Luis Díaz",
    "James Rodríguez",
    "Juan Fernando Quintero",
    "Moisés Caicedo",
    "Pervis Estupiñán",
    "Enner Valencia",
    "Antonio Valencia",
    "Ángel Mena",
    "Diego Godín",
    "Martín Cáceres",
    "Luis Suárez",
    "Diego Forlán",
    "Edinson Cavani",
    "Álvaro Recoba",
    "Diego Lugano",
    "Federico Valverde",
    "Darwin Núñez",
    "Manuel Neuer",
    "Marc-André ter Stegen",
    "Jan Oblak",
    "Alisson Becker",
    "Ederson",
    "Keylor Navas",
    "Hugo Sánchez",
    "Jorge Campos",
    "Rafael Márquez",
    "Cuauhtémoc Blanco",
    "Javier Hernández"
  ],
  "jugador_borroso": [
    {
      "nombre": "Lionel Messi",
      "imagen_url": "https://upload.wikimedia.org/wikipedia/commons/b/b2/Lionel_Messi_Argentina_v_Egypt_7_July_2026-112%28cropped%29.jpg"
    },
    {
      "nombre": "Cristiano Ronaldo",
      "imagen_url": "https://upload.wikimedia.org/wikipedia/commons/2/26/Cristiano_Ronaldo_Croatia_v_Portugal_2_July_2026-075_%28cropped%29.jpg"
    },
    {
      "nombre": "Diego Maradona",
      "imagen_url": "https://upload.wikimedia.org/wikipedia/commons/2/2c/Maradona-Mundial_86_con_la_copa.JPG"
    },
    {
      "nombre": "Pelé",
      "imagen_url": "https://upload.wikimedia.org/wikipedia/commons/5/5e/Pele_con_brasil_%28cropped%29.jpg"
    },
    {
      "nombre": "Zinedine Zidane",
      "imagen_url": "https://upload.wikimedia.org/wikipedia/commons/f/f3/Zinedine_Zidane_by_Tasnim_03.jpg"
    },
    {
      "nombre": "Ronaldinho",
      "imagen_url": "https://upload.wikimedia.org/wikipedia/commons/e/e8/Ronaldinho_in_2019.jpg"
    },
    {
      "nombre": "Ronaldo Nazário",
      "imagen_url": "https://upload.wikimedia.org/wikipedia/commons/7/74/051119SMcC0014.jpg"
    },
    {
      "nombre": "Neymar",
      "imagen_url": "https://upload.wikimedia.org/wikipedia/commons/c/c0/Neymar_Junior_Brazil_V_Morocco_13_June_2026-40.jpg"
    },
    {
      "nombre": "Kylian Mbappé",
      "imagen_url": "https://upload.wikimedia.org/wikipedia/commons/9/95/Kylian_Mbappe_France_v_Senegal_16_June_2026-391_%28cropped%29.jpg"
    },
    {
      "nombre": "Erling Haaland",
      "imagen_url": "https://upload.wikimedia.org/wikipedia/commons/4/43/Erling_Haaland_Morocco_v_Norway_7_June_2026-51.jpg"
    },
    {
      "nombre": "Robert Lewandowski",
      "imagen_url": "https://upload.wikimedia.org/wikipedia/commons/2/26/2019147183134_2019-05-27_Fussball_1.FC_Kaiserslautern_vs_FC_Bayern_M%C3%BCnchen_-_Sven_-_1D_X_MK_II_-_0228_-_B70I8527_%28cropped%29.jpg"
    },
    {
      "nombre": "Kevin De Bruyne",
      "imagen_url": "https://upload.wikimedia.org/wikipedia/commons/4/40/Kevin_De_Bruyne_USMNT_v_Belgium_Mar_28_2026-64_%28cropped%29.jpg"
    },
    {
      "nombre": "Luka Modrić",
      "imagen_url": "https://upload.wikimedia.org/wikipedia/commons/8/80/Luka_Modric_Croatia_v_Portugal_2_July_2026-055.jpg"
    },
    {
      "nombre": "Toni Kroos",
      "imagen_url": "https://upload.wikimedia.org/wikipedia/commons/6/64/Toni_Kroos_Real_Madrid_2021.jpg"
    },
    {
      "nombre": "Karim Benzema",
      "imagen_url": "https://upload.wikimedia.org/wikipedia/commons/5/5f/Karim_Benzema_Pick.jpg"
    },
    {
      "nombre": "Sergio Ramos",
      "imagen_url": "https://upload.wikimedia.org/wikipedia/commons/4/4b/Sergio_Ramos_Interview_2021_%28cropped%29.jpg"
    },
    {
      "nombre": "Andrés Iniesta",
      "imagen_url": "https://upload.wikimedia.org/wikipedia/commons/a/a5/Andr%C3%A9s_Iniesta_%28cropped%29.jpg"
    },
    {
      "nombre": "Xavi Hernández",
      "imagen_url": "https://upload.wikimedia.org/wikipedia/commons/5/53/Xavi_13981129001173637176666027076571.jpg"
    },
    {
      "nombre": "Gerard Piqué",
      "imagen_url": "https://upload.wikimedia.org/wikipedia/commons/f/f2/Gerard_Piqu%C3%A9_Euro_2012_vs_France_01.jpg"
    },
    {
      "nombre": "Iker Casillas",
      "imagen_url": "https://upload.wikimedia.org/wikipedia/commons/c/c8/Iker-Casillas-SportsTrade-2021-cropped.jpg"
    },
    {
      "nombre": "Manuel Neuer",
      "imagen_url": "https://upload.wikimedia.org/wikipedia/commons/1/10/20180602_FIFA_Friendly_Match_Austria_vs._Germany_Manuel_Neuer_850_0723.jpg"
    },
    {
      "nombre": "Gianluigi Buffon",
      "imagen_url": "https://upload.wikimedia.org/wikipedia/commons/thumb/6/6e/Norway_Italy_-_June_2025_E_20.jpg/3840px-Norway_Italy_-_June_2025_E_20.jpg"
    },
    {
      "nombre": "Thibaut Courtois",
      "imagen_url": "https://upload.wikimedia.org/wikipedia/commons/f/f7/Thibaut_Courtois_at_the_2018_World_Cup_%28cropped%29.jpg"
    },
    {
      "nombre": "Virgil van Dijk",
      "imagen_url": "https://upload.wikimedia.org/wikipedia/commons/5/5d/20160604_AUT_NED_8876_%28cropped%29.jpg"
    },
    {
      "nombre": "Mohamed Salah",
      "imagen_url": "https://upload.wikimedia.org/wikipedia/commons/a/a6/Mohamed_Salah_Argentina_v_Egypt_7_July_2026-163_%28cropped%29.jpg"
    },
    {
      "nombre": "Sadio Mané",
      "imagen_url": "https://upload.wikimedia.org/wikipedia/commons/9/92/Sadio_Mane_France_v_Senegal_16_June_2026-450.jpg"
    },
    {
      "nombre": "Harry Kane",
      "imagen_url": "https://upload.wikimedia.org/wikipedia/commons/e/e6/Harry_Kane_9_England_v_Ghana_at_2026_Fifa_World_Cup_by_YantsImages_01_%28cropped%29.jpg"
    },
    {
      "nombre": "Son Heung-min",
      "imagen_url": "https://upload.wikimedia.org/wikipedia/commons/b/b0/BFA_2023_-2_Heung-Min_Son_%28cropped%29.jpg"
    },
    {
      "nombre": "Antoine Griezmann",
      "imagen_url": "https://upload.wikimedia.org/wikipedia/commons/6/6e/FRA-ARG_%2810%29_%28cropped%29.jpg"
    },
    {
      "nombre": "Paul Pogba",
      "imagen_url": "https://upload.wikimedia.org/wikipedia/commons/c/cc/FRA-ARG_%2811%29_-_Paul_Pogba_%28cropped_2%29.jpg"
    },
    {
      "nombre": "N'Golo Kanté",
      "imagen_url": "https://upload.wikimedia.org/wikipedia/commons/c/c1/N%27Golo_Kante_France_v_Senegal_16_June_2026-397.jpg"
    },
    {
      "nombre": "Eden Hazard",
      "imagen_url": "https://upload.wikimedia.org/wikipedia/commons/6/68/Eden_Hazard_WC2022.jpg"
    },
    {
      "nombre": "Gareth Bale",
      "imagen_url": "https://upload.wikimedia.org/wikipedia/commons/1/1e/2022_FIFA_World_Cup_United_States_1%E2%80%931_Wales_-_%2832%29_%28cropped%29.jpg"
    },
    {
      "nombre": "Edinson Cavani",
      "imagen_url": "https://upload.wikimedia.org/wikipedia/commons/e/e9/PALMEIRAS_X_BOCA_JUNIORS_-_COPA_LIBERTADORES_2023_%2853286889335%29.jpg"
    },
    {
      "nombre": "Ángel Di María",
      "imagen_url": "https://upload.wikimedia.org/wikipedia/commons/8/8c/NIG-ARG_%285%29.jpg"
    },
    {
      "nombre": "Paulo Dybala",
      "imagen_url": "https://upload.wikimedia.org/wikipedia/commons/7/73/FC_Salzburg_gegen_AS_Roma_%28UEFA_Euroleague_play-off%2C_2023-02-16%29_38_-_Paulo_Dybala_%28cropped%29.jpg"
    },
    {
      "nombre": "Lautaro Martínez",
      "imagen_url": "https://upload.wikimedia.org/wikipedia/commons/e/e3/Lautaro_Martinez_Argentina_v_Egypt_7_July_2026-040.jpg"
    },
    {
      "nombre": "Emiliano Martínez",
      "imagen_url": "https://upload.wikimedia.org/wikipedia/commons/a/af/Emiliano_Martinez_Argentina_v_Egypt_7_July_2026-093.jpg"
    },
    {
      "nombre": "Rodrigo De Paul",
      "imagen_url": "https://upload.wikimedia.org/wikipedia/commons/b/b1/Rodrigo_De_Paul_Argentina_v_Egypt_7_July_2026-238_%28cropped%29.jpg"
    },
    {
      "nombre": "Enzo Fernández",
      "imagen_url": "https://upload.wikimedia.org/wikipedia/commons/f/f2/Enzo_Fernandez_Argentina_v_Egypt_7_July_2026-058.jpg"
    },
    {
      "nombre": "Alexis Mac Allister",
      "imagen_url": "https://upload.wikimedia.org/wikipedia/commons/5/59/Alexis_Mac_Allister_Argentina_v_Egypt_7_July_2026-182.jpg"
    },
    {
      "nombre": "Carlos Tévez",
      "imagen_url": "https://upload.wikimedia.org/wikipedia/commons/e/e6/InddelVal-Boca_%284%29.jpg"
    },
    {
      "nombre": "Sergio Agüero",
      "imagen_url": "https://upload.wikimedia.org/wikipedia/commons/7/7b/Ag%C3%BCero_in_2018.jpg"
    },
    {
      "nombre": "Javier Mascherano",
      "imagen_url": "https://upload.wikimedia.org/wikipedia/commons/9/9a/Javier_Mascherano_NE_Revolution_Inter_Miami_7.9.25-040_%28cropped%29.jpg"
    },
    {
      "nombre": "Juan Román Riquelme",
      "imagen_url": "https://upload.wikimedia.org/wikipedia/commons/b/ba/Juan_Rom%C3%A1n_Riquelme_-_2019.jpg"
    },
    {
      "nombre": "Pablo Aimar",
      "imagen_url": "https://upload.wikimedia.org/wikipedia/commons/d/da/Pablo_Aimar_Argentina_v_Egypt_7_July_2026-080.jpg"
    },
    {
      "nombre": "Hernán Crespo",
      "imagen_url": "https://upload.wikimedia.org/wikipedia/commons/9/9f/Chelsea_Legends_1_Inter_Forever_4_%2827457022797%29.jpg"
    },
    {
      "nombre": "Gabriel Batistuta",
      "imagen_url": "https://upload.wikimedia.org/wikipedia/commons/1/13/Omar_Batistuta_%282%29.jpg"
    },
    {
      "nombre": "Javier Zanetti",
      "imagen_url": "https://upload.wikimedia.org/wikipedia/commons/e/e7/Metalist-Inter_%282%29.jpg"
    },
    {
      "nombre": "Esteban Cambiasso",
      "imagen_url": "https://upload.wikimedia.org/wikipedia/commons/6/6d/Cambiasso_Inter_2013.jpg"
    },
    {
      "nombre": "Walter Samuel",
      "imagen_url": "https://upload.wikimedia.org/wikipedia/commons/d/df/Walter_Samuel_2022_%28cropped%29.jpg"
    },
    {
      "nombre": "Juan Sebastián Verón",
      "imagen_url": "https://upload.wikimedia.org/wikipedia/commons/2/20/JSV-Presidente-Estudiantes-2014.JPG"
    },
    {
      "nombre": "Rivaldo",
      "imagen_url": "https://upload.wikimedia.org/wikipedia/commons/b/b4/Rivaldo_bunyodkor_2010.jpg"
    },
    {
      "nombre": "Kaká",
      "imagen_url": "https://upload.wikimedia.org/wikipedia/commons/6/6d/Kak%C3%A1_visited_Stadium_St._Petersburg.jpg"
    },
    {
      "nombre": "Cafu",
      "imagen_url": "https://upload.wikimedia.org/wikipedia/commons/7/7a/14_06_2019_Abertura_da_Copa_Am%C3%A9rica_Brasil_2019_%2848064408836%29_%28cropped%29.jpg"
    },
    {
      "nombre": "Dani Alves",
      "imagen_url": "https://upload.wikimedia.org/wikipedia/commons/d/dd/07_07_2019_Final_da_Copa_Am%C3%A9rica_2019_%2848226649586%29_%28cropped%29.jpg"
    },
    {
      "nombre": "Thiago Silva",
      "imagen_url": "https://upload.wikimedia.org/wikipedia/commons/c/c8/20180610_FIFA_Friendly_Match_Austria_vs._Brazil_Thiago_Silva_850_1582.jpg"
    },
    {
      "nombre": "Casemiro",
      "imagen_url": "https://upload.wikimedia.org/wikipedia/commons/2/2f/Casemiro_Brazil_V_Morocco_13_June_2026-76_%28cropped%29.jpg"
    },
    {
      "nombre": "Rodrygo",
      "imagen_url": "https://upload.wikimedia.org/wikipedia/commons/0/05/Rodrygo_2023_%28cropped%29.jpg"
    },
    {
      "nombre": "Richarlison",
      "imagen_url": "https://upload.wikimedia.org/wikipedia/commons/5/5b/07_07_2019_Final_da_Copa_Am%C3%A9rica_2019_%2848226557731%29_%28cropped%29.jpg"
    },
    {
      "nombre": "Gabriel Jesus",
      "imagen_url": "https://upload.wikimedia.org/wikipedia/commons/8/87/20180610_FIFA_Friendly_Match_Austria_vs._Brazil_Gabriel_Jesus_850_1688.jpg"
    },
    {
      "nombre": "Romário",
      "imagen_url": "https://upload.wikimedia.org/wikipedia/commons/a/ad/Senadores_da_57%C2%AA_Legislatura_%2852689451805%29.jpg"
    },
    {
      "nombre": "Adriano",
      "imagen_url": "https://upload.wikimedia.org/wikipedia/commons/d/d7/Bust_Hadrian_Musei_Capitolini_MC817.jpg"
    },
    {
      "nombre": "Bebeto",
      "imagen_url": "https://upload.wikimedia.org/wikipedia/commons/8/85/Bebeto_cropped.jpg"
    },
    {
      "nombre": "Sócrates",
      "imagen_url": "https://upload.wikimedia.org/wikipedia/commons/b/bc/Socrate_du_Louvre.jpg"
    },
    {
      "nombre": "Garrincha",
      "imagen_url": "https://upload.wikimedia.org/wikipedia/commons/e/eb/MFdSantos-Garrincha.jpg"
    },
    {
      "nombre": "Franz Beckenbauer",
      "imagen_url": "https://upload.wikimedia.org/wikipedia/commons/5/56/Franz_Beckenbauer_%281975%29.jpg"
    },
    {
      "nombre": "Gerd Müller",
      "imagen_url": "https://upload.wikimedia.org/wikipedia/commons/3/32/Gerd_muller_figurita.jpg"
    },
    {
      "nombre": "Miroslav Klose",
      "imagen_url": "https://upload.wikimedia.org/wikipedia/commons/1/1f/FC_RB_Salzburg_gegen_SCR_Altach_%282023-03-19%29_44.jpg"
    },
    {
      "nombre": "Thomas Müller",
      "imagen_url": "https://upload.wikimedia.org/wikipedia/commons/a/aa/FC_Red_Bull_Salzburg_gegen_Bayern_M%C3%BCnchen_%282025-01-06_Testspiel%29_19.jpg"
    },
    {
      "nombre": "Philipp Lahm",
      "imagen_url": "https://upload.wikimedia.org/wikipedia/commons/8/8a/Philipp_Lahm_auf_der_Berlinale_2024%2C_Ausschnitt.jpg"
    },
    {
      "nombre": "Bastian Schweinsteiger",
      "imagen_url": "https://upload.wikimedia.org/wikipedia/commons/a/ac/Re-publica_23_-_Tag_3_%2852957826298%29_%28cropped%29.jpg"
    },
    {
      "nombre": "Mesut Özil",
      "imagen_url": "https://upload.wikimedia.org/wikipedia/commons/1/12/Mesut_%C3%96zil_at_Baku_before_2019_UEFA_Europe_League_Final.jpg"
    },
    {
      "nombre": "Marco Reus",
      "imagen_url": "https://upload.wikimedia.org/wikipedia/commons/c/cf/2023-08-12_TSV_Schott_Mainz_gegen_Borussia_Dortmund_%28DFB-Pokal_2023-24%29_by_Sandro_Halank%E2%80%93126.jpg"
    },
    {
      "nombre": "Mats Hummels",
      "imagen_url": "https://upload.wikimedia.org/wikipedia/commons/8/80/2023-08-12_TSV_Schott_Mainz_gegen_Borussia_Dortmund_%28DFB-Pokal_2023-24%29_by_Sandro_Halank%E2%80%93103.jpg"
    },
    {
      "nombre": "Joshua Kimmich",
      "imagen_url": "https://upload.wikimedia.org/wikipedia/commons/5/5d/Joshua_Kimmich_Ecuador_v_Germany_25_June_2026-149.jpg"
    },
    {
      "nombre": "Jamal Musiala",
      "imagen_url": "https://upload.wikimedia.org/wikipedia/commons/4/44/Jamal_Musiala_Ecuador_v_Germany_25_June_2026-174_%28cropped%29.jpg"
    },
    {
      "nombre": "Arjen Robben",
      "imagen_url": "https://upload.wikimedia.org/wikipedia/commons/4/42/Arjen_Robben_v_Shakhtar_2015_%28cropped%29.jpg"
    },
    {
      "nombre": "Franck Ribéry",
      "imagen_url": "https://upload.wikimedia.org/wikipedia/commons/b/bc/Franck_Ribery_2019_%28cropped%29.jpg"
    },
    {
      "nombre": "Robin van Persie",
      "imagen_url": "https://upload.wikimedia.org/wikipedia/commons/6/65/Loco-Fener_%2810%29.jpg"
    },
    {
      "nombre": "Wesley Sneijder",
      "imagen_url": "https://upload.wikimedia.org/wikipedia/commons/4/42/Wesley_Sneijder_%2815487233555%29_%28cropped%29.jpg"
    },
    {
      "nombre": "Clarence Seedorf",
      "imagen_url": "https://upload.wikimedia.org/wikipedia/commons/c/c2/Clarence_Seedorf_Introductory_Press_Conferences%2C_2_June_2025_-_40_%28cropped%29.jpg"
    },
    {
      "nombre": "Ruud Gullit",
      "imagen_url": "https://upload.wikimedia.org/wikipedia/commons/6/67/25th_Laureus_World_Sports_Awards_-_Ruud_Gullit_-_240422_131911_%28cropped%29.jpg"
    },
    {
      "nombre": "Marco van Basten",
      "imagen_url": "https://upload.wikimedia.org/wikipedia/commons/2/24/Marco_van_Basten_%28ca_2006%29.jpg"
    },
    {
      "nombre": "Johan Cruyff",
      "imagen_url": "https://upload.wikimedia.org/wikipedia/commons/6/69/Johan_Cruyff_1974c.jpg"
    },
    {
      "nombre": "Dennis Bergkamp",
      "imagen_url": "https://upload.wikimedia.org/wikipedia/commons/7/75/Dennis_Bergkamp_2014_%28cropped%29.jpg"
    },
    {
      "nombre": "Patrick Vieira",
      "imagen_url": "https://upload.wikimedia.org/wikipedia/commons/5/59/Patrick_Vieira_NYCFC.JPG"
    },
    {
      "nombre": "Thierry Henry",
      "imagen_url": "https://upload.wikimedia.org/wikipedia/commons/b/b9/Thierry_Henry_%2851649035951%29_%28cropped%29.jpg"
    },
    {
      "nombre": "Eric Cantona",
      "imagen_url": "https://upload.wikimedia.org/wikipedia/commons/f/f4/Eric_Cantona_Cannes_2009.jpg"
    },
    {
      "nombre": "Wayne Rooney",
      "imagen_url": "https://upload.wikimedia.org/wikipedia/commons/0/0c/Wayne-Rooney-2015-10-21.jpg"
    },
    {
      "nombre": "David Beckham",
      "imagen_url": "https://upload.wikimedia.org/wikipedia/commons/7/73/David_Beckham_UNICEF_%28cropped2%29.jpg"
    },
    {
      "nombre": "Steven Gerrard",
      "imagen_url": "https://upload.wikimedia.org/wikipedia/commons/d/d5/Steven_Gerrard_2018.jpg"
    },
    {
      "nombre": "Frank Lampard",
      "imagen_url": "https://upload.wikimedia.org/wikipedia/commons/8/8c/Frank_Lampard_2019.jpg"
    },
    {
      "nombre": "Rio Ferdinand",
      "imagen_url": "https://upload.wikimedia.org/wikipedia/commons/4/4c/Web_Summit_2015_-_Dublin%2C_Ireland_-_22183056474_%28cropped%29.jpg"
    },
    {
      "nombre": "Ashley Cole",
      "imagen_url": "https://upload.wikimedia.org/wikipedia/commons/d/d5/ACole.JPG"
    },
    {
      "nombre": "Ryan Giggs",
      "imagen_url": "https://upload.wikimedia.org/wikipedia/commons/1/18/Cskamu_17.jpg"
    },
    {
      "nombre": "Paul Scholes",
      "imagen_url": "https://upload.wikimedia.org/wikipedia/commons/c/c3/Paul_Scholes_2017.jpg"
    },
    {
      "nombre": "Didier Drogba",
      "imagen_url": "https://upload.wikimedia.org/wikipedia/commons/7/77/Didier_Drogba_%282019%29_%28cropped2%29.jpg"
    },
    {
      "nombre": "Samuel Eto'o",
      "imagen_url": "https://upload.wikimedia.org/wikipedia/commons/6/6a/Sammuel_Eto%27o_Fils_02.jpg"
    },
    {
      "nombre": "Yaya Touré",
      "imagen_url": "https://upload.wikimedia.org/wikipedia/commons/b/b7/Yaya_Tour%C3%A9_%28cropped%29.jpg"
    },
    {
      "nombre": "George Weah",
      "imagen_url": "https://upload.wikimedia.org/wikipedia/commons/7/7d/George_Weah_in_2019_%28cropped%29_mod-2.jpg"
    },
    {
      "nombre": "Riyad Mahrez",
      "imagen_url": "https://upload.wikimedia.org/wikipedia/commons/4/45/Mahrez_2021.jpg"
    },
    {
      "nombre": "Achraf Hakimi",
      "imagen_url": "https://upload.wikimedia.org/wikipedia/commons/f/f1/Achraf_Hakimi_vs_Niger%2C_5_Sept_2025.jpg"
    },
    {
      "nombre": "Victor Osimhen",
      "imagen_url": "https://upload.wikimedia.org/wikipedia/commons/3/34/Victor-osimhen-nigeria-2024-3-4.jpg"
    },
    {
      "nombre": "Khvicha Kvaratskhelia",
      "imagen_url": "https://upload.wikimedia.org/wikipedia/commons/4/4a/Kvaratskhelia_asse_psg_2425.png"
    },
    {
      "nombre": "Luis Figo",
      "imagen_url": "https://upload.wikimedia.org/wikipedia/commons/1/15/Luis_Figo_2023.jpg"
    },
    {
      "nombre": "Deco",
      "imagen_url": "https://upload.wikimedia.org/wikipedia/commons/f/fa/Deco_com_o_Fluminense_em_2013_%28cropped%29.jpg"
    },
    {
      "nombre": "Bruno Fernandes",
      "imagen_url": "https://upload.wikimedia.org/wikipedia/commons/c/c7/Bruno_Fernandes_USMNT_v_Portugal_Mar_31_2026-27_%28cropped%29.jpg"
    },
    {
      "nombre": "Bernardo Silva",
      "imagen_url": "https://upload.wikimedia.org/wikipedia/commons/c/cf/Bernardo_Silva_%28Isto_%C3%89_Gozar_Com_Quem_Trabalha%2C_2024%29.png"
    },
    {
      "nombre": "Rúben Dias",
      "imagen_url": "https://upload.wikimedia.org/wikipedia/commons/9/9a/Portugal_national_football_team_0866_%28R%C3%BAben_Dias%29.jpg"
    },
    {
      "nombre": "João Félix",
      "imagen_url": "https://upload.wikimedia.org/wikipedia/commons/1/1c/Joao_Felix_Croatia_v_Portugal_2_July_2026-007.jpg"
    },
    {
      "nombre": "Ricardo Quaresma",
      "imagen_url": "https://upload.wikimedia.org/wikipedia/commons/b/be/Ricardo_Quaresma_%28cropped%29_2.jpg"
    },
    {
      "nombre": "Radamel Falcao",
      "imagen_url": "https://upload.wikimedia.org/wikipedia/commons/8/87/Radamel_Falcao_Garc%C3%ADa_en_Millonarios.jpg"
    },
    {
      "nombre": "James Rodríguez",
      "imagen_url": "https://upload.wikimedia.org/wikipedia/commons/5/54/2019-03-09_Fu%C3%9Fball%2C_M%C3%A4nner%2C_1._Bundesliga%2C_FC_Bayern_M%C3%BCnchen_-_VfL_Wolfsburg_StP_2655_by_Stepro.jpg"
    },
    {
      "nombre": "Juan Cuadrado",
      "imagen_url": "https://upload.wikimedia.org/wikipedia/commons/8/8d/Juan_Cuadrado%2C_FC_Zenit_vs_Juventus_FC_%28UCL%29%3B_20_Oct_2021.png"
    },
    {
      "nombre": "Yerry Mina",
      "imagen_url": "https://upload.wikimedia.org/wikipedia/commons/b/bf/FWC_2018_-_Round_of_16_-_COL_v_ENG_-_Photo_103_%28cropped%29.jpg"
    },
    {
      "nombre": "David Villa",
      "imagen_url": "https://upload.wikimedia.org/wikipedia/commons/a/a4/Spain-Tahiti%2C_Confederations_Cup_2013_%2802%29_%28Villa_crop%29.jpg"
    },
    {
      "nombre": "Fernando Torres",
      "imagen_url": "https://upload.wikimedia.org/wikipedia/commons/5/57/Fernando_Torres_2017.jpg"
    },
    {
      "nombre": "Cesc Fàbregas",
      "imagen_url": "https://upload.wikimedia.org/wikipedia/commons/5/5b/2023_-_Cesc_Fabregas_%28cropped%29.jpg"
    },
    {
      "nombre": "David Silva",
      "imagen_url": "https://upload.wikimedia.org/wikipedia/commons/a/a6/David_Silva_2017.jpg"
    },
    {
      "nombre": "Santi Cazorla",
      "imagen_url": "https://upload.wikimedia.org/wikipedia/commons/c/cd/Santiago_Cazorla_-_Spain_vs._Chile%2C_10th_September_2013_%28cropped%29.jpg"
    },
    {
      "nombre": "Carles Puyol",
      "imagen_url": "https://upload.wikimedia.org/wikipedia/commons/6/65/Premios_Goya_2020_-_Carles_Pujol.jpg"
    },
    {
      "nombre": "Sergio Busquets",
      "imagen_url": "https://upload.wikimedia.org/wikipedia/commons/7/71/Sergio_Busquets_NE_Revolution_Inter_Miami_7.9.25-028_%28cropped%29.jpg"
    },
    {
      "nombre": "Zlatan Ibrahimović",
      "imagen_url": "https://upload.wikimedia.org/wikipedia/commons/0/09/Zlatan_Ibrahimovi%C4%87_June_2018.jpg"
    },
    {
      "nombre": "Andrea Pirlo",
      "imagen_url": "https://upload.wikimedia.org/wikipedia/commons/6/6e/20150616_-_Portugal_-_Italie_-_Gen%C3%A8ve_-_Andrea_Pirlo_%28cropped%29.jpg"
    },
    {
      "nombre": "Alessandro Del Piero",
      "imagen_url": "https://upload.wikimedia.org/wikipedia/commons/d/d3/25th_Laureus_World_Sports_Awards_-_Alessandro_Del_Piero_-_240421_155220_%28cropped%29.jpg"
    },
    {
      "nombre": "Francesco Totti",
      "imagen_url": "https://upload.wikimedia.org/wikipedia/commons/e/ea/KL-2018_%287%29.jpg"
    },
    {
      "nombre": "Fabio Cannavaro",
      "imagen_url": "https://upload.wikimedia.org/wikipedia/commons/8/8c/Fabio_Cannavaro_2017_Cropped.jpg"
    },
    {
      "nombre": "Paolo Maldini",
      "imagen_url": "https://upload.wikimedia.org/wikipedia/commons/0/0a/Paolo_Maldini_AC_Milan_Technical_director_2018.jpg"
    },
    {
      "nombre": "Leonardo Bonucci",
      "imagen_url": "https://upload.wikimedia.org/wikipedia/commons/6/62/20150616_-_Portugal_-_Italie_-_Gen%C3%A8ve_-_Leonardo_Bonucci.jpg"
    },
    {
      "nombre": "Giorgio Chiellini",
      "imagen_url": "https://upload.wikimedia.org/wikipedia/commons/b/b9/Sergio_Mattarella_meets_Italy_national_football_team_and_Matteo_Berrettini_%2812_July_2021%29_30_-_Chiellini_%28cropped%29.jpg"
    },
    {
      "nombre": "Daniele De Rossi",
      "imagen_url": "https://upload.wikimedia.org/wikipedia/commons/7/7d/Daniele_De_Rossi_BGR-ITA_2012.jpg"
    },
    {
      "nombre": "Mario Balotelli",
      "imagen_url": "https://upload.wikimedia.org/wikipedia/commons/f/f9/Mario_Balotelli_Euro_2012_vs_England_02.JPG"
    },
    {
      "nombre": "Hakim Ziyech",
      "imagen_url": "https://upload.wikimedia.org/wikipedia/commons/e/e1/Hakim_Ziyech_2021.jpg"
    },
    {
      "nombre": "Yassine Bounou",
      "imagen_url": "https://upload.wikimedia.org/wikipedia/commons/5/53/Yassine_Bono_%28cropped%29.jpg"
    },
    {
      "nombre": "Sofyan Amrabat",
      "imagen_url": "https://upload.wikimedia.org/wikipedia/commons/9/9f/Sofyan_Amrabat_Brazil_V_Morocco_13_June_2026-63.jpg"
    },
    {
      "nombre": "Michael Essien",
      "imagen_url": "https://upload.wikimedia.org/wikipedia/commons/4/4f/Essien_Real_Madrid.JPG"
    },
    {
      "nombre": "Pierre-Emerick Aubameyang",
      "imagen_url": "https://upload.wikimedia.org/wikipedia/commons/3/37/1_Pierre-Emerick_Aubameyang_%28cropped%29.jpg"
    },
    {
      "nombre": "Jay-Jay Okocha",
      "imagen_url": "https://upload.wikimedia.org/wikipedia/commons/7/7e/Match_legends_2017_CC_%285%29.jpg"
    },
    {
      "nombre": "Nwankwo Kanu",
      "imagen_url": "https://upload.wikimedia.org/wikipedia/commons/8/8d/1_nwankwo_kanu_2017_%28edited%29.jpg"
    },
    {
      "nombre": "Thomas Partey",
      "imagen_url": "https://upload.wikimedia.org/wikipedia/commons/4/42/ATL-Madrid-Lokomotiv001-Thomas_%28cropped%29.jpg"
    },
    {
      "nombre": "Park Ji-sung",
      "imagen_url": "https://upload.wikimedia.org/wikipedia/commons/4/4a/Park_Ji-sung_G20_Seoul_Summit_Ambassador_%28cropped%29.jpg"
    },
    {
      "nombre": "Keisuke Honda",
      "imagen_url": "https://upload.wikimedia.org/wikipedia/commons/7/79/Keisuke_Honda_2018_%28cropped%29_%28cropped%29.jpg"
    },
    {
      "nombre": "Shinji Kagawa",
      "imagen_url": "https://upload.wikimedia.org/wikipedia/commons/4/44/Shinji_Kagawa_2018.png"
    },
    {
      "nombre": "Takefusa Kubo",
      "imagen_url": "https://upload.wikimedia.org/wikipedia/commons/5/52/Takefusa_Kubo_1053.jpg"
    },
    {
      "nombre": "Mehdi Taremi",
      "imagen_url": "https://upload.wikimedia.org/wikipedia/commons/7/74/Iran_-_Japan%2C_AFC_Asian_Cup_2019_42_%28cropped%29.jpg"
    },
    {
      "nombre": "Tim Cahill",
      "imagen_url": "https://upload.wikimedia.org/wikipedia/commons/d/dc/Tim_Cahill_%2853557484101%29.jpg"
    },
    {
      "nombre": "Carlos Valderrama",
      "imagen_url": "https://upload.wikimedia.org/wikipedia/commons/3/34/El_Pibe_Valderrama.jpg"
    },
    {
      "nombre": "René Higuita",
      "imagen_url": "https://upload.wikimedia.org/wikipedia/commons/7/7a/Ren%C3%A9_Higuita%2C_2007.jpg"
    },
    {
      "nombre": "Arturo Vidal",
      "imagen_url": "https://upload.wikimedia.org/wikipedia/commons/a/a2/Chile_VS._Australia_%2813%29_2017-6-25_Arturo_Vidal.jpg"
    },
    {
      "nombre": "Alexis Sánchez",
      "imagen_url": "https://upload.wikimedia.org/wikipedia/commons/6/68/Alexis_S%C3%A1nchez_2016.jpg"
    },
    {
      "nombre": "José Luis Chilavert",
      "imagen_url": "https://upload.wikimedia.org/wikipedia/commons/e/e6/Chilavert_2014.jpg"
    },
    {
      "nombre": "Roque Santa Cruz",
      "imagen_url": "https://upload.wikimedia.org/wikipedia/commons/6/66/R._Santa_Cruz_Blackburn.jpg"
    },
    {
      "nombre": "Paolo Guerrero",
      "imagen_url": "https://upload.wikimedia.org/wikipedia/commons/3/3b/Paolo_Guerrero%2C_FIFA_Club_World_Cup_2012.jpg"
    },
    {
      "nombre": "Jefferson Farfán",
      "imagen_url": "https://upload.wikimedia.org/wikipedia/commons/c/c1/Jefferson_Farf%C3%A1n_Loko.jpg"
    },
    {
      "nombre": "Luis Díaz",
      "imagen_url": "https://upload.wikimedia.org/wikipedia/commons/c/c7/FC_RB_Salzburg_gegen_FC_Bayern_M%C3%BCnchen_%282026-01-06_Testspiel%29_40_%28Luiz_D%C3%ADaz%29.jpg"
    },
    {
      "nombre": "Moisés Caicedo",
      "imagen_url": "https://upload.wikimedia.org/wikipedia/commons/0/0e/Moises_Caicedo_Ecuador_v_Germany_25_June_2026-051_%28cropped%29.jpg"
    },
    {
      "nombre": "Pervis Estupiñán",
      "imagen_url": "https://upload.wikimedia.org/wikipedia/commons/5/54/Pervis_Estupinan_Cote_D%27Ivoire_v_Ecuador_14_June_2026-73.jpg"
    },
    {
      "nombre": "Enner Valencia",
      "imagen_url": "https://upload.wikimedia.org/wikipedia/commons/4/4f/Enner_Valencia_Cote_D%27Ivoire_v_Ecuador_14_June_2026-95.jpg"
    },
    {
      "nombre": "Antonio Valencia",
      "imagen_url": "https://upload.wikimedia.org/wikipedia/commons/f/fc/AntonioValencia2022.jpg"
    },
    {
      "nombre": "Diego Godín",
      "imagen_url": "https://upload.wikimedia.org/wikipedia/commons/9/91/Loko-AM2018_%285%29.jpg"
    },
    {
      "nombre": "Diego Forlán",
      "imagen_url": "https://upload.wikimedia.org/wikipedia/commons/thumb/b/b6/Diego_Forl%C3%A1n_28_jan_2018.jpg/1920px-Diego_Forl%C3%A1n_28_jan_2018.jpg"
    },
    {
      "nombre": "Federico Valverde",
      "imagen_url": "https://upload.wikimedia.org/wikipedia/commons/7/73/Federico_Valverde_2021_%28cropped%29.jpg"
    },
    {
      "nombre": "Darwin Núñez",
      "imagen_url": "https://upload.wikimedia.org/wikipedia/commons/1/11/Darwin_N%C3%BA%C3%B1ez_%28cropped%29.jpg"
    },
    {
      "nombre": "Marc-André ter Stegen",
      "imagen_url": "https://upload.wikimedia.org/wikipedia/commons/9/97/Marc-Andre_Ter_Stegen_ACCI_FCBARCELONA_Turisme_Catalunya_gira_pretemporada_CATPRESS.jpg"
    },
    {
      "nombre": "Jan Oblak",
      "imagen_url": "https://upload.wikimedia.org/wikipedia/commons/a/a1/Jan_Oblak_2019.jpg"
    },
    {
      "nombre": "Alisson Becker",
      "imagen_url": "https://upload.wikimedia.org/wikipedia/commons/4/4f/Alisson_Becker_Brazil_V_Morocco_13_June_2026-117_%28cropped%29.jpg"
    },
    {
      "nombre": "Keylor Navas",
      "imagen_url": "https://upload.wikimedia.org/wikipedia/commons/d/dc/Keylor_Navas_2018_%28cropped%29.jpg"
    },
    {
      "nombre": "Hugo Sánchez",
      "imagen_url": "https://upload.wikimedia.org/wikipedia/commons/5/52/Hugo_S%C3%A1nchez_1988_%28cropped%29.jpg"
    },
    {
      "nombre": "Rafael Márquez",
      "imagen_url": "https://upload.wikimedia.org/wikipedia/commons/b/b2/Mex-Kor_%2851%29.jpg"
    }
  ]
}
